examples/__init__.py
examples/advanced_agent.py
examples/hackthon_qacase_agent.py
examples/multimodal_agent.py
examples/simple_agent.py
pinai_agent_sdk/__init__.py
pinai_agent_sdk/constants.py
pinai_agent_sdk/pinai_agent_sdk.py
pinai_agent_sdk-0.1.23.dist-info/LICENSE
pinai_agent_sdk-0.1.23.dist-info/METADATA
pinai_agent_sdk-0.1.23.dist-info/WHEEL
pinai_agent_sdk-0.1.23.dist-info/top_level.txt
pinai_agent_sdk-0.1.23.dist-info/RECORD
