Metadata-Version: 2.2
Name: pinai-agent-sdk
Version: 0.1.23
Summary: SDK for PINAI Agent API
Home-page: https://pinai.io
Author: smile
Author-email: smile@pinai.io
Project-URL: Bug Tracker, https://github.com/yourusername/pinai-agent-sdk/issues
Project-URL: Documentation, https://docs.pinai.io
Project-URL: Source Code, https://github.com/yourusername/pinai-agent-sdk
Keywords: pinai,agent,sdk,api,machine learning,ai
Classifier: Development Status :: 3 - Alpha
Classifier: Intended Audience :: Developers
Classifier: Topic :: Software Development :: Libraries :: Python Modules
Classifier: Programming Language :: Python :: 3
Classifier: Programming Language :: Python :: 3.10
Classifier: Programming Language :: Python :: 3.11
Classifier: License :: OSI Approved :: MIT License
Classifier: Operating System :: OS Independent
Requires-Python: >=3.10
License-File: LICENSE
Requires-Dist: fastapi>=0.68.0
Requires-Dist: uvicorn>=0.15.0
Requires-Dist: pydantic>=1.8.0
Requires-Dist: requests>=2.26.0
Requires-Dist: python-dotenv>=0.19.0
Requires-Dist: web3
Requires-Dist: eth-account
Dynamic: author
Dynamic: author-email
Dynamic: classifier
Dynamic: description
Dynamic: description-content-type
Dynamic: home-page
Dynamic: keywords
Dynamic: project-url
Dynamic: requires-dist
Dynamic: requires-python
Dynamic: summary
